<?xml version="1.0" encoding="utf-8"?>
<clothing-items>
 <clothing>
  <id>
   828506315
  </id>
  <name>
   Brooks Shoes S-1824
  </name>
  <category>
   Shoes
  </category>
  <size>
   XXL
  </size>
  <color>
   Голубой
  </color>
  <material>
   Шерсть
  </material>
  <price>
   548039
  </price>
  <rating>
   2.97
  </rating>
  <reviews>
   762296
  </reviews>
  <sporty>
   yes
  </sporty>
 </clothing>
 <clothing>
  <id>
   634168657
  </id>
  <name>
   New Balance T-shirt E-4918
  </name>
  <category>
   T-shirt
  </category>
  <size>
   XXL
  </size>
  <color>
   Голубой
  </color>
  <material>
   Полиэстер
  </material>
  <price>
   408028
  </price>
  <rating>
   4.59
  </rating>
  <reviews>
   450234
  </reviews>
  <exclusive>
   no
  </exclusive>
 </clothing>
 <clothing>
  <id>
   412062688
  </id>
  <name>
   Fila Shirt L-1063
  </name>
  <category>
   Shirt
  </category>
  <size>
   XL
  </size>
  <color>
   Зеленый
  </color>
  <material>
   Шелк
  </material>
  <price>
   440530
  </price>
  <rating>
   4.64
  </rating>
  <reviews>
   126178
  </reviews>
  <new>
   +
  </new>
  <exclusive>
   no
  </exclusive>
  <sporty>
   no
  </sporty>
 </clothing>
 <clothing>
  <id>
   371984918
  </id>
  <name>
   Addidas Umbrellas V-6882
  </name>
  <category>
   Umbrellas
  </category>
  <size>
   M
  </size>
  <color>
   Голубой
  </color>
  <material>
   Шерсть
  </material>
  <price>
   296647
  </price>
  <rating>
   2.14
  </rating>
  <reviews>
   316722
  </reviews>
  <new>
   -
  </new>
  <exclusive>
   no
  </exclusive>
  <sporty>
   no
  </sporty>
 </clothing>
 <clothing>
  <id>
   298219035
  </id>
  <name>
   PleinSport Jacket M-4648
  </name>
  <category>
   Jacket
  </category>
  <size>
   M
  </size>
  <color>
   Красный
  </color>
  <material>
   Кожа
  </material>
  <price>
   845989
  </price>
  <rating>
   2.19
  </rating>
  <reviews>
   758050
  </reviews>
  <new>
   -
  </new>
  <exclusive>
   no
  </exclusive>
  <sporty>
   yes
  </sporty>
 </clothing>
 <clothing>
  <id>
   842338629
  </id>
  <name>
   Adidas Gloves R-1143
  </name>
  <category>
   Gloves
  </category>
  <size>
   M
  </size>
  <color>
   Фиолетовый
  </color>
  <material>
   Хлопок
  </material>
  <price>
   938615
  </price>
  <rating>
   2.12
  </rating>
  <reviews>
   164312
  </reviews>
  <exclusive>
   no
  </exclusive>
 </clothing>
 <clothing>
  <id>
   873238471
  </id>
  <name>
   Nike Hat J-1379
  </name>
  <category>
   Hat
  </category>
  <size>
   XL
  </size>
  <color>
   Синий
  </color>
  <material>
   Вискоза
  </material>
  <price>
   801202
  </price>
  <rating>
   2.2
  </rating>
  <reviews>
   376592
  </reviews>
  <sporty>
   no
  </sporty>
 </clothing>
 <clothing>
  <id>
   562529764
  </id>
  <name>
   Adidas Dress P-6989
  </name>
  <category>
   Dress
  </category>
  <size>
   XL
  </size>
  <color>
   Оранжевый
  </color>
  <material>
   Полиэстер
  </material>
  <price>
   371947
  </price>
  <rating>
   3.63
  </rating>
  <reviews>
   298672
  </reviews>
  <exclusive>
   yes
  </exclusive>
 </clothing>
 <clothing>
  <id>
   209748377
  </id>
  <name>
   New Balance Gloves S-6529
  </name>
  <category>
   Gloves
  </category>
  <size>
   L
  </size>
  <color>
   Красный
  </color>
  <material>
   Кожа
  </material>
  <price>
   323589
  </price>
  <rating>
   3.63
  </rating>
  <reviews>
   301498
  </reviews>
  <new>
   +
  </new>
  <exclusive>
   no
  </exclusive>
  <sporty>
   no
  </sporty>
 </clothing>
 <clothing>
  <id>
   158783671
  </id>
  <name>
   Fila Blouse A-3091
  </name>
  <category>
   Blouse
  </category>
  <size>
   L
  </size>
  <color>
   Зеленый
  </color>
  <material>
   Вискоза
  </material>
  <price>
   283968
  </price>
  <rating>
   1.64
  </rating>
  <reviews>
   647708
  </reviews>
  <new>
   -
  </new>
  <exclusive>
   no
  </exclusive>
 </clothing>
 <clothing>
  <id>
   197804769
  </id>
  <name>
   Addidas Jeans A-9796
  </name>
  <category>
   Jeans
  </category>
  <size>
   S
  </size>
  <color>
   Синий
  </color>
  <material>
   Полиэстер
  </material>
  <price>
   310754
  </price>
  <rating>
   1.41
  </rating>
  <reviews>
   927864
  </reviews>
  <exclusive>
   yes
  </exclusive>
 </clothing>
 <clothing>
  <id>
   197588345
  </id>
  <name>
   PleinSport Shirt G-3487
  </name>
  <category>
   Shirt
  </category>
  <size>
   S
  </size>
  <color>
   Фиолетовый
  </color>
  <material>
   Лен
  </material>
  <price>
   950971
  </price>
  <rating>
   2.42
  </rating>
  <reviews>
   418411
  </reviews>
  <sporty>
   no
  </sporty>
 </clothing>
 <clothing>
  <id>
   621733095
  </id>
  <name>
   Addidas Shoes C-4510
  </name>
  <category>
   Shoes
  </category>
  <size>
   XL
  </size>
  <color>
   Красный
  </color>
  <material>
   Вискоза
  </material>
  <price>
   945807
  </price>
  <rating>
   3.74
  </rating>
  <reviews>
   684464
  </reviews>
  <new>
   -
  </new>
  <sporty>
   yes
  </sporty>
 </clothing>
 <clothing>
  <id>
   345687608
  </id>
  <name>
   DC T-shirt Y-6442
  </name>
  <category>
   T-shirt
  </category>
  <size>
   S
  </size>
  <color>
   Оранжевый
  </color>
  <material>
   Вискоза
  </material>
  <price>
   705082
  </price>
  <rating>
   4.36
  </rating>
  <reviews>
   636131
  </reviews>
  <new>
   +
  </new>
  <exclusive>
   no
  </exclusive>
  <sporty>
   no
  </sporty>
 </clothing>
 <clothing>
  <id>
   943080738
  </id>
  <name>
   Ellesse Socks R-2036
  </name>
  <category>
   Socks
  </category>
  <size>
   XXL
  </size>
  <color>
   Голубой
  </color>
  <material>
   Вискоза
  </material>
  <price>
   241129
  </price>
  <rating>
   3.8
  </rating>
  <reviews>
   765543
  </reviews>
  <new>
   -
  </new>
 </clothing>
 <clothing>
  <id>
   329145533
  </id>
  <name>
   PleinSport Umbrellas D-2914
  </name>
  <category>
   Umbrellas
  </category>
  <size>
   S
  </size>
  <color>
   Синий
  </color>
  <material>
   Шерсть
  </material>
  <price>
   428669
  </price>
  <rating>
   3.94
  </rating>
  <reviews>
   989385
  </reviews>
  <new>
   +
  </new>
  <exclusive>
   yes
  </exclusive>
  <sporty>
   no
  </sporty>
 </clothing>
 <clothing>
  <id>
   240998045
  </id>
  <name>
   Ellesse Shirt X-7713
  </name>
  <category>
   Shirt
  </category>
  <size>
   S
  </size>
  <color>
   Оранжевый
  </color>
  <material>
   Кожа
  </material>
  <price>
   788188
  </price>
  <rating>
   4.03
  </rating>
  <reviews>
   124786
  </reviews>
  <new>
   -
  </new>
  <sporty>
   no
  </sporty>
 </clothing>
 <clothing>
  <id>
   835486146
  </id>
  <name>
   Brooks Socks J-4861
  </name>
  <category>
   Socks
  </category>
  <size>
   M
  </size>
  <color>
   Голубой
  </color>
  <material>
   Нейлон
  </material>
  <price>
   687126
  </price>
  <rating>
   3.79
  </rating>
  <reviews>
   522174
  </reviews>
  <sporty>
   no
  </sporty>
 </clothing>
 <clothing>
  <id>
   385537595
  </id>
  <name>
   Asics Jacket E-2071
  </name>
  <category>
   Jacket
  </category>
  <size>
   M
  </size>
  <color>
   Синий
  </color>
  <material>
   Нейлон
  </material>
  <price>
   175067
  </price>
  <rating>
   2.82
  </rating>
  <reviews>
   868166
  </reviews>
  <new>
   +
  </new>
  <sporty>
   no
  </sporty>
 </clothing>
 <clothing>
  <id>
   844960490
  </id>
  <name>
   Asics Shoes K-2826
  </name>
  <category>
   Shoes
  </category>
  <size>
   M
  </size>
  <color>
   Желтый
  </color>
  <material>
   Нейлон
  </material>
  <price>
   357919
  </price>
  <rating>
   4.93
  </rating>
  <reviews>
   729457
  </reviews>
  <exclusive>
   yes
  </exclusive>
  <sporty>
   no
  </sporty>
 </clothing>
 <clothing>
  <id>
   718244347
  </id>
  <name>
   Adidas Hat E-4168
  </name>
  <category>
   Hat
  </category>
  <size>
   XXL
  </size>
  <color>
   Фиолетовый
  </color>
  <material>
   Нейлон
  </material>
  <price>
   253527
  </price>
  <rating>
   4.56
  </rating>
  <reviews>
   717867
  </reviews>
  <sporty>
   yes
  </sporty>
 </clothing>
 <clothing>
  <id>
   546848365
  </id>
  <name>
   PleinSport Hat E-8248
  </name>
  <category>
   Hat
  </category>
  <size>
   M
  </size>
  <color>
   Оранжевый
  </color>
  <material>
   Шерсть
  </material>
  <price>
   198045
  </price>
  <rating>
   3.01
  </rating>
  <reviews>
   650894
  </reviews>
  <new>
   +
  </new>
  <exclusive>
   no
  </exclusive>
 </clothing>
 <clothing>
  <id>
   688501724
  </id>
  <name>
   Addidas Belts H-9080
  </name>
  <category>
   Belts
  </category>
  <size>
   XL
  </size>
  <color>
   Синий
  </color>
  <material>
   Лен
  </material>
  <price>
   213210
  </price>
  <rating>
   4.05
  </rating>
  <reviews>
   946480
  </reviews>
  <sporty>
   no
  </sporty>
 </clothing>
 <clothing>
  <id>
   904029329
  </id>
  <name>
   Adidas Umbrellas C-6478
  </name>
  <category>
   Umbrellas
  </category>
  <size>
   L
  </size>
  <color>
   Оранжевый
  </color>
  <material>
   Лен
  </material>
  <price>
   198116
  </price>
  <rating>
   1.72
  </rating>
  <reviews>
   662717
  </reviews>
 </clothing>
 <clothing>
  <id>
   118056282
  </id>
  <name>
   DC T-shirt S-5715
  </name>
  <category>
   T-shirt
  </category>
  <size>
   L
  </size>
  <color>
   Желтый
  </color>
  <material>
   Полиэстер
  </material>
  <price>
   616861
  </price>
  <rating>
   4.42
  </rating>
  <reviews>
   3692
  </reviews>
  <new>
   +
  </new>
 </clothing>
 <clothing>
  <id>
   381709553
  </id>
  <name>
   Under Armour Shirt E-9424
  </name>
  <category>
   Shirt
  </category>
  <size>
   XXL
  </size>
  <color>
   Оранжевый
  </color>
  <material>
   Вискоза
  </material>
  <price>
   482450
  </price>
  <rating>
   4.53
  </rating>
  <reviews>
   636363
  </reviews>
  <new>
   -
  </new>
  <sporty>
   no
  </sporty>
 </clothing>
 <clothing>
  <id>
   317160856
  </id>
  <name>
   Under Armour Jacket G-3906
  </name>
  <category>
   Jacket
  </category>
  <size>
   M
  </size>
  <color>
   Желтый
  </color>
  <material>
   Полиэстер
  </material>
  <price>
   746715
  </price>
  <rating>
   4.4
  </rating>
  <reviews>
   222205
  </reviews>
  <new>
   +
  </new>
  <sporty>
   yes
  </sporty>
 </clothing>
 <clothing>
  <id>
   216845150
  </id>
  <name>
   New Balance Socks K-4507
  </name>
  <category>
   Socks
  </category>
  <size>
   M
  </size>
  <color>
   Красный
  </color>
  <material>
   Полиэстер
  </material>
  <price>
   699209
  </price>
  <rating>
   2.54
  </rating>
  <reviews>
   757537
  </reviews>
  <new>
   -
  </new>
  <sporty>
   no
  </sporty>
 </clothing>
</clothing-items>
